{
  "id": "669ef9af-ee91-4e1b-a6fd-ec49f3c10892",
  "deletedAt": null,
  "createdAt": "2022-05-23T22:16:15.589Z",
  "createdBy": "e5dba747-be62-49be-a7ba-71cf27b17174",
  "index": -1,
  "updatedAt": "2022-07-08T13:33:03.137Z",
  "updatedBy": "e5dba747-be62-49be-a7ba-71cf27b17174",
  "title": "Partner with CharmVerse",
  "content": {
    "type": "doc",
    "content": [
      {
        "type": "heading",
        "attrs": {
          "level": 1
        },
        "content": [
          {
            "text": "Description",
            "type": "text"
          }
        ]
      },
      {
        "type": "paragraph",
        "content": [
          {
            "text": "Write a description of the task here...",
            "type": "text"
          }
        ]
      },
      {
        "type": "heading",
        "attrs": {
          "level": 1
        },
        "content": [
          {
            "text": "To-do",
            "type": "text"
          }
        ]
      },
      {
        "type": "bulletList",
        "attrs": {
          "tight": false
        },
        "content": [
          {
            "type": "listItem",
            "attrs": {
              "todoChecked": false
            },
            "content": [
              {
                "type": "paragraph",
                "content": [
                  {
                    "text": "...",
                    "type": "text"
                  }
                ]
              }
            ]
          }
        ]
      },
      {
        "type": "bulletList",
        "attrs": {
          "tight": false
        },
        "content": [
          {
            "type": "listItem",
            "attrs": {
              "todoChecked": false
            },
            "content": [
              {
                "type": "paragraph",
                "content": [
                  {
                    "text": "...",
                    "type": "text"
                  }
                ]
              }
            ]
          }
        ]
      },
      {
        "type": "paragraph"
      }
    ]
  },
  "contentText": "DescriptionWrite a description of the task here...To-do......",
  "headerImage": null,
  "icon": "",
  "path": "page-7758744277066407",
  "parentId": "99388498-3fee-435c-8908-5ab634a0fec0",
  "spaceId": "da74cab3-c2b6-40bb-8734-0de5375b0fce",
  "type": "card",
  "boardId": null,
  "autoGenerated": false,
  "cardId": "669ef9af-ee91-4e1b-a6fd-ec49f3c10892",
  "fullWidth": false,
  "card": {
    "id": "669ef9af-ee91-4e1b-a6fd-ec49f3c10892",
    "deletedAt": null,
    "createdAt": "2022-05-23T22:16:15.589Z",
    "createdBy": "e5dba747-be62-49be-a7ba-71cf27b17174",
    "updatedAt": "2022-06-17T19:13:21.093Z",
    "updatedBy": "e5dba747-be62-49be-a7ba-71cf27b17174",
    "spaceId": "da74cab3-c2b6-40bb-8734-0de5375b0fce",
    "parentId": "99388498-3fee-435c-8908-5ab634a0fec0",
    "rootId": "99388498-3fee-435c-8908-5ab634a0fec0",
    "schema": 1,
    "type": "card",
    "title": "Card 3",
    "fields": {
      "icon": "",
      "isTemplate": false,
      "properties": {
        "03289657-299f-453b-a1d8-54d8b3b85851": "ddae6548-e379-47be-9a54-46982072f66a",
        "2b3cc0fd-3174-4b60-bb28-a4f4fa03350e": ["9db45552-dd20-45cc-b577-e5a34205042c"],
        "ab46872a-c754-4813-9114-372e923cc66a": "79ef1f7f-56da-48dd-a4d7-4a2a4dae5166",
        "ae50984b-38af-48a8-9494-2cb1b4f71694": "dc521ceb-495e-40cc-940e-3b1cafc7a2e1"
      },
      "headerImage": null,
      "contentOrder": []
    }
  }
}
